pydron_dataflow/__init__.py
pydron_dataflow/utils.py
pydron_dataflow/dataflow/__init__.py
pydron_dataflow/dataflow/graph.py
pydron_dataflow/dataflow/refine.py
pydron_dataflow/dataflow/tasks.py
pydron_dataflow/dataflow/test_graph.py
pydron_dataflow/dataflow/test_refine.py
pydron_dataflow/dataflow/utils.py
pydron_dataflow/interpreter/__init__.py
pydron_dataflow/interpreter/graphdecorator.py
pydron_dataflow/interpreter/test_graphdecorator.py
pydron_dataflow/interpreter/test_traverser.py
pydron_dataflow/interpreter/traverser.py
pydron_dataflow-0.2.6.dist-info/LICENSE
pydron_dataflow-0.2.6.dist-info/METADATA
pydron_dataflow-0.2.6.dist-info/WHEEL
pydron_dataflow-0.2.6.dist-info/top_level.txt
pydron_dataflow-0.2.6.dist-info/RECORD
